wf_rdbms/__init__.py
wf_rdbms/database.py
wf_rdbms/database_pandas.py
wf_rdbms/utils.py
wf_rdbms_python-0.0.2.dist-info/LICENSE
wf_rdbms_python-0.0.2.dist-info/METADATA
wf_rdbms_python-0.0.2.dist-info/WHEEL
wf_rdbms_python-0.0.2.dist-info/top_level.txt
wf_rdbms_python-0.0.2.dist-info/RECORD
