Metadata-Version: 2.1
Name: wf-rdbms-python
Version: 0.0.2
Summary: Python tools for defining and interacting with simple relational databases
Home-page: https://github.com/WildflowerSchools/wf-rdbms-python
Author: Theodore Quinn
Author-email: ted.quinn@wildflowerschools.org
License: UNKNOWN
Keywords: database
Platform: UNKNOWN
Classifier: Intended Audience :: Developers
Classifier: License :: OSI Approved :: MIT License
Classifier: Operating System :: OS Independent
Classifier: Programming Language :: Python
Requires-Dist: numpy (>=1.19)
Requires-Dist: pandas (>=1.1)
